quark_plugin_ghz/__init__.py
quark_plugin_ghz/ghz.py
quark_plugin_ghz-0.0.1.dist-info/licenses/LICENSE
quark_plugin_ghz-0.0.1.dist-info/licenses/NOTICE
quark_plugin_ghz-0.0.1.dist-info/METADATA
quark_plugin_ghz-0.0.1.dist-info/WHEEL
quark_plugin_ghz-0.0.1.dist-info/top_level.txt
quark_plugin_ghz-0.0.1.dist-info/RECORD
